spudlang/FormatCheck.py
spudlang/Ingredient.py
spudlang/MyNumber.py
spudlang/Pattern.py
spudlang/ResultsTree.py
spudlang/Rule.py
spudlang/RuleOutput.py
spudlang/SourceVersionCheck.py
spudlang/SpudLexer.py
spudlang/SpudLoader.py
spudlang/SpudParser.py
spudlang/__init__.py
spudlang/__main__.py
spudlang-0.5.1.dist-info/LICENSE.txt
spudlang-0.5.1.dist-info/METADATA
spudlang-0.5.1.dist-info/WHEEL
spudlang-0.5.1.dist-info/top_level.txt
spudlang-0.5.1.dist-info/RECORD
