Metadata-Version: 2.1
Name: spudlang
Version: 0.5.1
Summary: Domain-specific programming language for creating shopping lists
Home-page: https://github.com/aaronstanek/spudlang
Author: Aaron Stanek
Author-email: amr.stanek@gmail.com
Project-URL: Bug Tracker, https://github.com/aaronstanek/spudlang/issues
Classifier: Programming Language :: Python :: 3
Classifier: License :: OSI Approved :: MIT License
Classifier: Operating System :: OS Independent
Requires-Python: ~=3.6
License-File: LICENSE.txt
Requires-Dist: antlr4-python3-runtime (==4.9.2)
